imperial_dateutil/__init__.py
imperial_dateutil/core/__init__.py
imperial_dateutil/core/era_indomitus.py
imperial_dateutil/core/imperial.py
imperial_dateutil-0.1.3.dist-info/LICENSE
imperial_dateutil-0.1.3.dist-info/WHEEL
imperial_dateutil-0.1.3.dist-info/METADATA
imperial_dateutil-0.1.3.dist-info/RECORD
